make_clean.py
make_clean-2.0.1.dist-info/DESCRIPTION.rst
make_clean-2.0.1.dist-info/METADATA
make_clean-2.0.1.dist-info/RECORD
make_clean-2.0.1.dist-info/WHEEL
make_clean-2.0.1.dist-info/entry_points.txt
make_clean-2.0.1.dist-info/metadata.json
make_clean-2.0.1.dist-info/top_level.txt
