Metadata-Version: 2.0
Name: make-clean
Version: 2.0.1
Summary: A Cleanup Utility
Home-page: https://github.com/jptomo/make-clean.py
Author: Tomohiro NAKAMURA
Author-email: quickness.net@gmail.com
License: MIT License
Platform: UNKNOWN
Classifier: Development Status :: 5 - Production/Stable
Classifier: License :: OSI Approved :: MIT License
Provides-Extra: pypi
Requires-Dist: wheel; extra == 'pypi'
Provides-Extra: test
Requires-Dist: pytest; extra == 'test'
